{
  "POIs": [
    {
      "fit": [
        1.001051425933838,
        1.0035815238952637,
        2.171081781387329
      ],
      "name": "r"
    }
  ],
  "method": "default",
  "params": [
    {
      "fit": [
        5563.982421875,
        5563.982421875,
        5636.14990234375
      ],
      "groups": [],
      "impact_r": 0.0362931489944458,
      "name": "Background_fail_HIGH_bin_1-1",
      "prefit": [
        5564.0,
        5564.0,
        5564.0
      ],
      "r": [
        1.0013351440429688,
        1.0017205476760864,
        1.0380136966705322
      ],
      "type": "Unconstrained"
    },
    {
      "fit": [
        116.9996109008789,
        116.9996109008789,
        125.9902114868164
      ],
      "groups": [],
      "impact_r": 0.2022920846939087,
      "name": "Background_fail_HIGH_bin_10-1",
      "prefit": [
        117.0,
        117.0,
        117.0
      ],
      "r": [
        1.0013362169265747,
        1.0017205476760864,
        1.2040126323699951
      ],
      "type": "Unconstrained"
    },
    {
      "fit": [
        2492.989013671875,
        2492.989013671875,
        2540.689453125
      ],
      "groups": [],
      "impact_r": 0.04130661487579346,
      "name": "Background_fail_HIGH_bin_2-1",
      "prefit": [
        2493.0,
        2493.0,
        2493.0
      ],
      "r": [
        1.0013351440429688,
        1.0017205476760864,
        1.0430271625518799
      ],
      "type": "Unconstrained"
    },
    {
      "fit": [
        1213.9925537109375,
        1213.9925537109375,
        1246.810302734375
      ],
      "groups": [],
      "impact_r": 0.03781867027282715,
      "name": "Background_fail_HIGH_bin_3-1",
      "prefit": [
        1214.0,
        1214.0,
        1214.0
      ],
      "r": [
        1.0013351440429688,
        1.0017205476760864,
        1.0395392179489136
      ],
      "type": "Unconstrained"
    },
    {
      "fit": [
        681.9910888671875,
        681.9910888671875,
        706.1857299804688
      ],
      "groups": [],
      "impact_r": 0.02494102716445923,
      "name": "Background_fail_HIGH_bin_4-1",
      "prefit": [
        682.0,
        682.0,
        682.0
      ],
      "r": [
        1.0013377666473389,
        1.0017205476760864,
        0.9767795205116272
      ],
      "type": "Unconstrained"
    },
    {
      "fit": [
        430.9805603027344,
        430.9805603027344,
        449.68145751953125
      ],
      "groups": [],
      "impact_r": 0.27883875370025635,
      "name": "Background_fail_HIGH_bin_5-1",
      "prefit": [
        431.0,
        431.0,
        431.0
      ],
      "r": [
        1.001357078552246,
        1.0017205476760864,
        0.7228817939758301
      ],
      "type": "Unconstrained"
    },
    {
      "fit": [
        286.9819641113281,
        286.9819641113281,
        301.9319763183594
      ],
      "groups": [],
      "impact_r": 0.3247763514518738,
      "name": "Background_fail_HIGH_bin_6-1",
      "prefit": [
        287.0,
        287.0,
        287.0
      ],
      "r": [
        1.0013645887374878,
        1.0017205476760864,
        0.6769441962242126
      ],
      "type": "Unconstrained"
    },
    {
      "fit": [
        201.99620056152344,
        201.99620056152344,
        214.5161590576172
      ],
      "groups": [],
      "impact_r": 0.04706704616546631,
      "name": "Background_fail_HIGH_bin_7-1",
      "prefit": [
        202.0,
        202.0,
        202.0
      ],
      "r": [
        1.0013378858566284,
        1.0017205476760864,
        1.0487875938415527
      ],
      "type": "Unconstrained"
    },
    {
      "fit": [
        150.9983673095703,
        150.9983673095703,
        161.62806701660156
      ],
      "groups": [],
      "impact_r": 0.11686193943023682,
      "name": "Background_fail_HIGH_bin_8-1",
      "prefit": [
        151.0,
        151.0,
        151.0
      ],
      "r": [
        1.001335859298706,
        1.0017205476760864,
        1.1185824871063232
      ],
      "type": "Unconstrained"
    },
    {
      "fit": [
        104.99933624267578,
        104.99933624267578,
        113.6910171508789
      ],
      "groups": [],
      "impact_r": 0.15105390548706055,
      "name": "Background_fail_HIGH_bin_9-1",
      "prefit": [
        105.0,
        105.0,
        105.0
      ],
      "r": [
        1.0013349056243896,
        1.0017205476760864,
        1.152774453163147
      ],
      "type": "Unconstrained"
    },
    {
      "fit": [
        672494.4375,
        672494.4375,
        673307.6875
      ],
      "groups": [],
      "impact_r": 0.002152681350708008,
      "name": "Background_fail_LOW_bin_2-1",
      "prefit": [
        672494.0,
        672494.0,
        672494.0
      ],
      "r": [
        1.0013362169265747,
        1.0017205476760864,
        0.9995678663253784
      ],
      "type": "Unconstrained"
    },
    {
      "fit": [
        152032.0,
        152032.0,
        152418.328125
      ],
      "groups": [],
      "impact_r": 0.018361330032348633,
      "name": "Background_fail_LOW_bin_3-1",
      "prefit": [
        152032.0,
        152032.0,
        152032.0
      ],
      "r": [
        1.001330852508545,
        1.0017205476760864,
        1.020081877708435
      ],
      "type": "Unconstrained"
    },
    {
      "fit": [
        42692.9609375,
        42692.9609375,
        42896.796875
      ],
      "groups": [],
      "impact_r": 0.032939791679382324,
      "name": "Background_fail_LOW_bin_4-1",
      "prefit": [
        42693.0,
        42693.0,
        42693.0
      ],
      "r": [
        1.0013335943222046,
        1.0017205476760864,
        1.0346603393554688
      ],
      "type": "Unconstrained"
    },
    {
      "fit": [
        14176.9716796875,
        14176.9716796875,
        14293.4296875
      ],
      "groups": [],
      "impact_r": 0.02625739574432373,
      "name": "Background_fail_SIG_bin_1-1",
      "prefit": [
        14177.0,
        14177.0,
        14177.0
      ],
      "r": [
        1.0013349056243896,
        1.0017205476760864,
        1.0279779434204102
      ],
      "type": "Unconstrained"
    },
    {
      "fit": [
        0.11004556715488434,
        0.11004556715488434,
        0.13751082122325897
      ],
      "groups": [],
      "impact_r": 0.0017731785774230957,
      "name": "Background_rpf_2x0_par0",
      "prefit": [
        0.1,
        0.1,
        0.1
      ],
      "r": [
        1.001168966293335,
        1.0017205476760864,
        0.9999473690986633
      ],
      "type": "Unconstrained"
    },
    {
      "fit": [
        50.0,
        55.027618408203125,
        100.0
      ],
      "groups": [],
      "impact_r": 0.010333657264709473,
      "name": "Background_rpf_2x0_par1",
      "prefit": [
        50.0,
        50.0,
        50.0
      ],
      "r": [
        1.0026233196258545,
        1.0017205476760864,
        1.012054204940796
      ],
      "type": "Unconstrained"
    },
    {
      "fit": [
        -11.693985939025879,
        -0.0043252138420939445,
        0.0
      ],
      "groups": [],
      "impact_r": 0.5727680921554565,
      "name": "Background_rpf_2x0_par2",
      "prefit": [
        0.0,
        0.0,
        0.0
      ],
      "r": [
        1.574488639831543,
        1.0017205476760864,
        1.0011351108551025
      ],
      "type": "Unconstrained"
    },
    {
      "fit": [
        0.049029603600502014,
        0.09086509793996811,
        0.10000000149011612
      ],
      "groups": [],
      "impact_r": 0.2932314872741699,
      "name": "Background_rpf_2x0_par3",
      "prefit": [
        0.1,
        0.1,
        0.1
      ],
      "r": [
        1.2949520349502563,
        1.0017205476760864,
        1.0325896739959717
      ],
      "type": "Unconstrained"
    },
    {
      "fit": [
        -1.0000009536743164,
        1.22587198347901e-06,
        1.0000009536743164
      ],
      "groups": [],
      "impact_r": 0.00043582916259765625,
      "name": "RNN",
      "prefit": [
        -0.9999999999999999,
        0.0,
        0.9999999999999999
      ],
      "r": [
        1.0012863874435425,
        1.0017222166061401,
        1.0013478994369507
      ],
      "type": "Gaussian"
    },
    {
      "fit": [
        -0.9999998211860657,
        2.941126922451076e-06,
        0.9999741911888123
      ],
      "groups": [],
      "impact_r": 0.0007703304290771484,
      "name": "lumi",
      "prefit": [
        -0.9999999999999999,
        0.0,
        0.9999999999999999
      ],
      "r": [
        1.0018459558486938,
        1.0017204284667969,
        1.0009500980377197
      ],
      "type": "Gaussian"
    },
    {
      "fit": [
        -0.9991056323051453,
        -7.662546522624325e-06,
        0.9986249208450317
      ],
      "groups": [],
      "impact_r": 0.007200300693511963,
      "name": "pT",
      "prefit": [
        -0.9999999999999999,
        0.0,
        0.9999999999999999
      ],
      "r": [
        1.0058003664016724,
        1.001718521118164,
        0.9945182204246521
      ],
      "type": "Gaussian"
    },
    {
      "fit": [
        0.0,
        0.0,
        0.9966021180152893
      ],
      "groups": [],
      "impact_r": 0.00038874149322509766,
      "name": "t0",
      "prefit": [
        -0.9999999999999999,
        0.0,
        0.9999999999999999
      ],
      "r": [
        1.0013318061828613,
        1.0017205476760864,
        1.0013318061828613
      ],
      "type": "Gaussian"
    }
  ]
}