{
  "POIs": [
    {
      "fit": [
        -10.0,
        0.999999463558197,
        3.6862027645111084
      ],
      "name": "r"
    }
  ],
  "method": "default",
  "params": [
    {
      "fit": [
        5509.13818359375,
        5564.0,
        5619.2568359375
      ],
      "groups": [],
      "impact_r": 0.4821315407752991,
      "name": "Background_fail_HIGH_bin_1-1",
      "prefit": [
        5564.0,
        5564.0,
        5564.0
      ],
      "r": [
        0.5417535305023193,
        0.9999993443489075,
        1.4821308851242065
      ],
      "type": "Unconstrained"
    },
    {
      "fit": [
        109.17237854003906,
        117.0,
        125.228515625
      ],
      "groups": [],
      "impact_r": 0.23043149709701538,
      "name": "Background_fail_HIGH_bin_10-1",
      "prefit": [
        117.0,
        117.0,
        117.0
      ],
      "r": [
        0.8179500102996826,
        0.9999993443489075,
        1.2304308414459229
      ],
      "type": "Unconstrained"
    },
    {
      "fit": [
        2456.56201171875,
        2493.0,
        2529.8271484375
      ],
      "groups": [],
      "impact_r": 0.4518802762031555,
      "name": "Background_fail_HIGH_bin_2-1",
      "prefit": [
        2493.0,
        2493.0,
        2493.0
      ],
      "r": [
        0.574604868888855,
        0.9999993443489075,
        1.451879620552063
      ],
      "type": "Unconstrained"
    },
    {
      "fit": [
        1188.794677734375,
        1214.0,
        1239.5869140625
      ],
      "groups": [],
      "impact_r": 0.410500705242157,
      "name": "Background_fail_HIGH_bin_3-1",
      "prefit": [
        1214.0,
        1214.0,
        1214.0
      ],
      "r": [
        0.6160835027694702,
        0.9999993443489075,
        1.4105000495910645
      ],
      "type": "Unconstrained"
    },
    {
      "fit": [
        663.2259521484375,
        682.0,
        701.1532592773438
      ],
      "groups": [],
      "impact_r": 0.3576435446739197,
      "name": "Background_fail_HIGH_bin_4-1",
      "prefit": [
        682.0,
        682.0,
        682.0
      ],
      "r": [
        0.6715359687805176,
        0.9999993443489075,
        1.3576428890228271
      ],
      "type": "Unconstrained"
    },
    {
      "fit": [
        416.15673828125,
        431.0,
        446.2198486328125
      ],
      "groups": [],
      "impact_r": 0.23733478784561157,
      "name": "Background_fail_HIGH_bin_5-1",
      "prefit": [
        431.0,
        431.0,
        431.0
      ],
      "r": [
        0.7882677912712097,
        0.9999993443489075,
        1.237334132194519
      ],
      "type": "Unconstrained"
    },
    {
      "fit": [
        274.8664245605469,
        287.0,
        299.48504638671875
      ],
      "groups": [],
      "impact_r": 0.27782291173934937,
      "name": "Background_fail_HIGH_bin_6-1",
      "prefit": [
        287.0,
        287.0,
        287.0
      ],
      "r": [
        1.2778222560882568,
        0.9999993443489075,
        0.7636792659759521
      ],
      "type": "Unconstrained"
    },
    {
      "fit": [
        190.31008911132812,
        202.0,
        213.92031860351562
      ],
      "groups": [],
      "impact_r": 1.3097609877586365,
      "name": "Background_fail_HIGH_bin_7-1",
      "prefit": [
        202.0,
        202.0,
        202.0
      ],
      "r": [
        2.309760332107544,
        0.9999993443489075,
        8.543456351617351e-05
      ],
      "type": "Unconstrained"
    },
    {
      "fit": [
        140.4304656982422,
        151.0,
        161.7205810546875
      ],
      "groups": [],
      "impact_r": 1.4795724749565125,
      "name": "Background_fail_HIGH_bin_8-1",
      "prefit": [
        151.0,
        151.0,
        151.0
      ],
      "r": [
        2.47957181930542,
        0.9999993443489075,
        0.00036412329063750803
      ],
      "type": "Unconstrained"
    },
    {
      "fit": [
        97.66339111328125,
        105.0,
        112.68891906738281
      ],
      "groups": [],
      "impact_r": 0.34142357110977173,
      "name": "Background_fail_HIGH_bin_9-1",
      "prefit": [
        105.0,
        105.0,
        105.0
      ],
      "r": [
        1.3414229154586792,
        0.9999993443489075,
        0.7308183312416077
      ],
      "type": "Unconstrained"
    },
    {
      "fit": [
        671708.0625,
        672494.0,
        673280.5625
      ],
      "groups": [],
      "impact_r": 0.26511436700820923,
      "name": "Background_fail_LOW_bin_2-1",
      "prefit": [
        672494.0,
        672494.0,
        672494.0
      ],
      "r": [
        1.2651137113571167,
        0.9999993443489075,
        0.7412945628166199
      ],
      "type": "Unconstrained"
    },
    {
      "fit": [
        151734.890625,
        152032.0,
        152329.53125
      ],
      "groups": [],
      "impact_r": 0.25437045097351074,
      "name": "Background_fail_LOW_bin_3-1",
      "prefit": [
        152032.0,
        152032.0,
        152032.0
      ],
      "r": [
        0.7456288933753967,
        0.9999993443489075,
        1.2523897886276245
      ],
      "type": "Unconstrained"
    },
    {
      "fit": [
        42539.0859375,
        42693.0,
        42847.32421875
      ],
      "groups": [],
      "impact_r": 0.4567173719406128,
      "name": "Background_fail_LOW_bin_4-1",
      "prefit": [
        42693.0,
        42693.0,
        42693.0
      ],
      "r": [
        0.5432819724082947,
        0.9999993443489075,
        1.4348443746566772
      ],
      "type": "Unconstrained"
    },
    {
      "fit": [
        14088.796875,
        14177.0,
        14265.6025390625
      ],
      "groups": [],
      "impact_r": 0.5035536885261536,
      "name": "Background_fail_SIG_bin_1-1",
      "prefit": [
        14177.0,
        14177.0,
        14177.0
      ],
      "r": [
        0.5240464806556702,
        0.9999993443489075,
        1.503553032875061
      ],
      "type": "Unconstrained"
    },
    {
      "fit": [
        0.049153633415699005,
        0.09999988228082657,
        0.1514834761619568
      ],
      "groups": [],
      "impact_r": 1.3618618845939636,
      "name": "Background_rpf_expo_par0",
      "prefit": [
        0.1,
        0.1,
        0.1
      ],
      "r": [
        0.00013027785462327302,
        0.9999993443489075,
        2.361861228942871
      ],
      "type": "Unconstrained"
    },
    {
      "fit": [
        0.09791383892297745,
        0.10000000894069672,
        0.10208636522293091
      ],
      "groups": [],
      "impact_r": 0.9365024343132973,
      "name": "Background_rpf_expo_par1",
      "prefit": [
        0.1,
        0.1,
        0.1
      ],
      "r": [
        0.0634969100356102,
        0.9999993443489075,
        1.9208173751831055
      ],
      "type": "Unconstrained"
    },
    {
      "fit": [
        -1.0,
        1.2774992175224043e-09,
        0.9999998211860657
      ],
      "groups": [],
      "impact_r": 0.0010429024696350098,
      "name": "RNN",
      "prefit": [
        -0.9999999999999999,
        0.0,
        0.9999999999999999
      ],
      "r": [
        0.9999993443489075,
        0.9999993443489075,
        1.0010422468185425
      ],
      "type": "Gaussian"
    },
    {
      "fit": [
        -0.9999974370002747,
        0.0,
        0.9999975562095642
      ],
      "groups": [],
      "impact_r": 0.03026401996612549,
      "name": "lumi",
      "prefit": [
        -0.9999999999999999,
        0.0,
        0.9999999999999999
      ],
      "r": [
        1.0267254114151,
        1.0,
        0.9697359800338745
      ],
      "type": "Gaussian"
    },
    {
      "fit": [
        -0.9996730089187622,
        1.0413512541163072e-07,
        0.9997239112854004
      ],
      "groups": [],
      "impact_r": 0.010746955871582031,
      "name": "pT",
      "prefit": [
        -0.9999999999999999,
        0.0,
        0.9999999999999999
      ],
      "r": [
        1.0045671463012695,
        0.9999993443489075,
        0.9892523884773254
      ],
      "type": "Gaussian"
    },
    {
      "fit": [
        -1.0,
        0.0,
        1.0
      ],
      "groups": [],
      "impact_r": 5.4836273193359375e-06,
      "name": "t0",
      "prefit": [
        -0.9999999999999999,
        0.0,
        0.9999999999999999
      ],
      "r": [
        0.9999938607215881,
        0.9999993443489075,
        0.9999938607215881
      ],
      "type": "Gaussian"
    }
  ]
}